maige/__init__.py
maige/functions.py
maige/generator.py
maige-0.0.3.dist-info/LICENSE.md
maige-0.0.3.dist-info/METADATA
maige-0.0.3.dist-info/WHEEL
maige-0.0.3.dist-info/top_level.txt
maige-0.0.3.dist-info/RECORD
