Metadata-Version: 2.1
Name: maige
Version: 0.0.3
Summary: Generate beautiful images and animations using mathematical formulae.
Author-email: Chahak Mehta <chahakmehta013@gmail.com>
Project-URL: Homepage, https://github.com/chahak13/maige
Project-URL: Bug Tracker, https://github.com/chahak13/maige/issues
Keywords: art,math,animation,generativeart
Classifier: Programming Language :: Python :: 3
Classifier: License :: OSI Approved :: MIT License
Classifier: Operating System :: OS Independent
Requires-Python: >=3.7
License-File: LICENSE.md
Requires-Dist: numpy
Requires-Dist: matplotlib
Requires-Dist: tqdm
